roulier_gls_fr/__init__.py
roulier_gls_fr-0.1.0.dist-info/WHEEL
roulier_gls_fr-0.1.0.dist-info/METADATA
roulier_gls_fr-0.1.0.dist-info/RECORD
