Metadata-Version: 2.1
Name: roulier-gls-fr
Version: 0.1.0
Summary: Send parcels with GLS France delivery carrier. Carrier return parcel label and traceability url
Home-page: https://github.com/akretion.roulier-gls-fr
Keywords: carrier,logistics,GLS,parcel,transporteur
Author: David Béal
Author-email: david.beal@akretion.com
Requires-Python: >=3.6,<4.0
Classifier: Development Status :: 2 - Pre-Alpha
Classifier: Environment :: Console
Classifier: Intended Audience :: Customer Service
Classifier: Intended Audience :: Manufacturing
Classifier: Natural Language :: French
Classifier: Operating System :: OS Independent
Classifier: Programming Language :: Python :: 3
Classifier: Programming Language :: Python :: 3.6
Classifier: Programming Language :: Python :: 3.7
Classifier: Topic :: Office/Business
Requires-Dist: pycountry (>=18.12,<19.0)
Requires-Dist: roulier (>=0.3.7,<0.4.0)
Project-URL: Repository, https://github.com/akretion.roulier-gls-fr
